nlp_knowledge_cli.py
knowledge_search_engine/__init__.py
knowledge_search_engine/audio_from_video.py
knowledge_search_engine/image_namer.py
knowledge_search_engine/images_to_text.py
knowledge_search_engine/speach_recogn.py
knowledge_search_engine/video_to_text.py
utils/__init__.py
utils/image_processing.py
utils/profiling.py
utils/text_processing.py
NLPKnowledge-0.0.2.7.dist-info/LICENSE
NLPKnowledge-0.0.2.7.dist-info/METADATA
NLPKnowledge-0.0.2.7.dist-info/WHEEL
NLPKnowledge-0.0.2.7.dist-info/entry_points.txt
NLPKnowledge-0.0.2.7.dist-info/top_level.txt
NLPKnowledge-0.0.2.7.dist-info/RECORD
