Metadata-Version: 2.1
Name: NLPKnowledge
Version: 0.0.2.7
Summary: Package to make sense of images with text information
Home-page: UNKNOWN
Author: Oleksandr Maistrov
Author-email: maistrovas@gmail.com
License: UNKNOWN
Platform: UNKNOWN
Classifier: Development Status :: 3 - Alpha
Requires-Python: >=3.4
Requires-Dist: click (==6.7)
Requires-Dist: py (==1.4.34)
Requires-Dist: pytest (==3.2.3)
Requires-Dist: pytesseract (==0.3.0)
Requires-Dist: summa (==1.2.0)
Requires-Dist: spacy (==2.2.1)
Requires-Dist: Pillow (==6.2.0)
